TracLDAPAuth-1.2.1.dist-info/DESCRIPTION.rst
TracLDAPAuth-1.2.1.dist-info/METADATA
TracLDAPAuth-1.2.1.dist-info/RECORD
TracLDAPAuth-1.2.1.dist-info/WHEEL
TracLDAPAuth-1.2.1.dist-info/entry_points.txt
TracLDAPAuth-1.2.1.dist-info/metadata.json
TracLDAPAuth-1.2.1.dist-info/top_level.txt
ldapauth/__init__.py
ldapauth/store.py
