Metadata-Version: 2.0
Name: TracLDAPAuth
Version: 1.2.1
Summary: An AccountManager password store that uses python-ldap to check against an LDAP server.
Home-page: http://trac-hacks.org/wiki/TracLdapAuthPlugin
Author: Nikolaos Papagrigoriou
Author-email: nikolaos@papagrigoriou.com
License: BSD
Keywords: trac plugin accountmanager
Platform: UNKNOWN
Classifier: Framework :: Trac
Requires-Dist: Trac
Requires-Dist: TracAccountManager
Requires-Dist: python-ldap
